pywhook/__init__.py
pywhook/pywhook.py
pywhook/types/__init__.py
pywhook/types/endpoint_config.py
pywhook/types/request_headers.py
pywhook/types/webhook_request.py
pywhook/types/errors/__init__.py
pywhook/types/errors/webhook_error.py
pywhook-1.1.5.dist-info/licenses/LICENSE
pywhook-1.1.5.dist-info/METADATA
pywhook-1.1.5.dist-info/WHEEL
pywhook-1.1.5.dist-info/top_level.txt
pywhook-1.1.5.dist-info/RECORD
