Metadata-Version: 2.4
Name: pywhook
Version: 1.1.5
Summary: Python wrapper for webhook.site API
Home-page: https://github.com/cvcvka5/pywhook
Author: Ulus Vatansever
Author-email: ulusvatansever@gmail.com
Classifier: Programming Language :: Python :: 3
Classifier: License :: OSI Approved :: MIT License
Classifier: Operating System :: OS Independent
Requires-Python: >=3.7
License-File: LICENSE
Requires-Dist: requests>=2.20.0
Dynamic: author
Dynamic: author-email
Dynamic: classifier
Dynamic: description
Dynamic: description-content-type
Dynamic: home-page
Dynamic: license-file
Dynamic: requires-dist
Dynamic: requires-python
Dynamic: summary
